{"status":"1","version":"8","content":[{"name":"中欧心血管学院（PCI\/动脉硬化学院）","start":"08:30","end":"12:00","room":"4","data":[{"id":"03-03","title":"中欧心血管学院（PCI\/动脉硬化学院）","time":"2016-07-24 08:30~12:00","place":"4"}]},{"name":"疑难病例论坛一","start":"08:30","end":"10:30","room":"2","data":[{"id":"03-07","title":"疑难病例论坛一","time":"2016-07-24 08:30~10:30","place":"2"}]},{"name":"肺栓塞及肺动脉高压","start":"08:30","end":"12:00","room":"9","data":[{"id":"03-11-001","title":"肺栓塞及肺动脉高压（第一场）","time":"2016-07-24 08:30~10:00","place":"9"},{"id":"03-11-002","title":"肺栓塞及肺动脉高压（第二场）","time":"2016-07-24 10:00~12:00","place":"9"}]},{"name":"关注女人心-女性心脏健康论坛","start":"08:30","end":"12:00","room":"5","data":[{"id":"03-13-001","title":"关注女人心-女性心脏健康论坛（第一场）","time":"2016-07-24 08:30~09:45","place":"5"},{"id":"03-13-002","title":"关注女人心-女性心脏健康论坛（第二场）","time":"2016-07-24 09:45~10:50","place":"5"},{"id":"03-13-003","title":"关注女人心-女性心脏健康论坛（第三场）","time":"2016-07-24 10:50~11:55","place":"5"}]},{"name":"疑难病例论坛二","start":"10:30","end":"12:00","room":"2","data":[{"id":"03-16","title":"疑难病例论坛二","time":"2016-07-24 10:30~12:00","place":"2"}]},{"name":"老年心血管及相关疾病论坛","start":"08:30","end":"12:00","room":"3","data":[{"id":"03-18-001","title":"老年心血管及相关疾病论坛（第一场）","time":"2016-07-24 08:30~10:30","place":"3"},{"id":"03-18-002","title":"老年心血管及相关疾病论坛（第二场）","time":"2016-07-24 10:20~12:00","place":"3"}]},{"name":"全军心血管青年委员会读书报告会","start":"08:30","end":"12:00","room":"10","data":[{"id":"03-19","title":"全军心血管青年委员会读书报告会","time":"2016-07-24 08:30~12:00","place":"10"}]},{"name":"心电图论坛 第三部分","start":"08:30","end":"12:00","room":"6","data":[{"id":"03-22-03-001","title":"心电图论坛 第三部分（病例分析版块）","time":"2016-07-24 10:10~11:50","place":"6"},{"id":"03-22-03-002","title":"心电图论坛 第三部分（起搏器心电图版块）","time":"2016-07-24 08:30~10:10","place":"6"}]},{"name":"心衰高血压论坛","start":"08:30","end":"12:00","room":"7","data":[{"id":"03-23-001","title":"心衰高血压论坛（第一场）","time":"2016-07-24 08:30~10:00","place":"7"},{"id":"03-23-002","title":"心衰高血压论坛（第二场）","time":"2016-07-24 10:00~12:00","place":"7"}]},{"name":"心脏电生理与起搏 第三部分","start":"08:30","end":"12:00","room":"8","data":[{"id":"03-24-03-01","title":"心脏电生理与起搏 第三部分（第一场）","time":"2016-07-24 08:30~10:10","place":"8"},{"id":"03-24-03-02","title":"心脏电生理与起搏 第三部分（第二场）","time":"2016-07-24 10:20~12:00","place":"8"}]}]}